__init__.py
plantfem.py
soy.json
soyleaf.json
soyroot.json
soystem.json
plantfem-21.10.1.34.data/data/soy.json
plantfem-21.10.1.34.data/data/soyleaf.json
plantfem-21.10.1.34.data/data/soyroot.json
plantfem-21.10.1.34.data/data/soystem.json
plantfem.egg-info/PKG-INFO
plantfem.egg-info/SOURCES.txt
plantfem.egg-info/dependency_links.txt
plantfem.egg-info/requires.txt
plantfem.egg-info/top_level.txt
plantfem-21.10.1.34.dist-info/METADATA
plantfem-21.10.1.34.dist-info/WHEEL
plantfem-21.10.1.34.dist-info/top_level.txt
plantfem-21.10.1.34.dist-info/RECORD
